adb_messenger/__init__.py
adb_messenger/application.py
adb_messenger/client.py
adb_messenger/connection.py
adb_messenger/device.py
adb_messenger/keycode.py
adb_messenger/protocol.py
adb_messenger/command/__init__.py
adb_messenger/command/host/__init__.py
adb_messenger/command/serial/__init__.py
adb_messenger/command/transport/__init__.py
adb_messenger/plugins/__init__.py
adb_messenger/plugins/client/__init__.py
adb_messenger/plugins/device/__init__.py
adb_messenger/plugins/device/input.py
adb_messenger/plugins/device/stat.py
adb_messenger/plugins/device/traffic.py
adb_messenger/plugins/device/utils.py
adb_messenger/plugins/device/wm.py
adb_messenger/sync/__init__.py
adb_messenger/sync/stats.py
adb_messenger/utils/__init__.py
adb_messenger/utils/logger.py
pure_python_adb_homeassistant-0.1.7.dev0.dist-info/LICENSE
pure_python_adb_homeassistant-0.1.7.dev0.dist-info/METADATA
pure_python_adb_homeassistant-0.1.7.dev0.dist-info/WHEEL
pure_python_adb_homeassistant-0.1.7.dev0.dist-info/top_level.txt
pure_python_adb_homeassistant-0.1.7.dev0.dist-info/RECORD
